Metadata-Version: 2.1
Name: thabox
Version: 0.0.7
Summary: ThaBox is an open-source, terminal-based, retro-modern chat application where clients can connect to chatrooms and talk anonymously.
Home-page: https://github.com/MikeNoCap/ThaBox
Author: The Jazzed Jerboas
Author-email: thorvaldsenmikkel@gmail.com
License: MIT
Project-URL: Bug Tracker, https://github.com/MikeNoCap/ThaBox/issues
Platform: UNKNOWN
